interprompt/.syncCommitId.remote
interprompt/.syncCommitId.this
interprompt/__init__.py
interprompt/jinja_template.py
interprompt/multilang_prompt.py
interprompt/prompt_factory.py
interprompt/util/__init__.py
interprompt/util/class_decorators.py
serena/__init__.py
serena/agent.py
serena/agno.py
serena/analytics.py
serena/cli.py
serena/code_editor.py
serena/constants.py
serena/dashboard.py
serena/gui_log_viewer.py
serena/mcp.py
serena/project.py
serena/prompt_factory.py
serena/symbol.py
serena/text_utils.py
serena/config/__init__.py
serena/config/context_mode.py
serena/config/serena_config.py
serena/generated/generated_prompt_factory.py
serena/resources/project.template.yml
serena/resources/serena_config.template.yml
serena/resources/config/contexts/agent.yml
serena/resources/config/contexts/chatgpt.yml
serena/resources/config/contexts/codex.yml
serena/resources/config/contexts/context.template.yml
serena/resources/config/contexts/desktop-app.yml
serena/resources/config/contexts/ide-assistant.yml
serena/resources/config/contexts/oaicompat-agent.yml
serena/resources/config/internal_modes/jetbrains.yml
serena/resources/config/modes/editing.yml
serena/resources/config/modes/interactive.yml
serena/resources/config/modes/mode.template.yml
serena/resources/config/modes/no-onboarding.yml
serena/resources/config/modes/onboarding.yml
serena/resources/config/modes/one-shot.yml
serena/resources/config/modes/planning.yml
serena/resources/config/prompt_templates/simple_tool_outputs.yml
serena/resources/config/prompt_templates/system_prompt.yml
serena/resources/dashboard/dashboard.js
serena/resources/dashboard/index.html
serena/resources/dashboard/jquery.min.js
serena/resources/dashboard/serena-icon-16.png
serena/resources/dashboard/serena-icon-32.png
serena/resources/dashboard/serena-icon-48.png
serena/resources/dashboard/serena-logs-dark-mode.png
serena/resources/dashboard/serena-logs.png
serena/tools/__init__.py
serena/tools/cmd_tools.py
serena/tools/config_tools.py
dungngo_serena_agent-0.1.5.dist-info/METADATA
dungngo_serena_agent-0.1.5.dist-info/WHEEL
dungngo_serena_agent-0.1.5.dist-info/entry_points.txt
dungngo_serena_agent-0.1.5.dist-info/licenses/LICENSE
dungngo_serena_agent-0.1.5.dist-info/RECORD
